passthesalt/__init__.py
passthesalt/cli.py
passthesalt/core.py
passthesalt/crypto.py
passthesalt/exceptions.py
passthesalt/model.py
passthesalt/remote.py
passthesalt-3.2.2.dist-info/LICENSE
passthesalt-3.2.2.dist-info/METADATA
passthesalt-3.2.2.dist-info/WHEEL
passthesalt-3.2.2.dist-info/entry_points.txt
passthesalt-3.2.2.dist-info/top_level.txt
passthesalt-3.2.2.dist-info/RECORD
