Metadata-Version: 2.1
Name: passthesalt
Version: 3.2.2
Summary: Deterministic password generation and password storage.
Home-page: https://github.com/rossmacarthur/passthesalt
Author: Ross MacArthur
Author-email: ross@macarthur.io
License: MIT
Download-URL: https://github.com/rossmacarthur/passthesalt/archive/3.2.2.tar.gz
Project-URL: Issue Tracker, https://github.com/rossmacarthur/passthesalt/issues
Keywords: password manager pbkdf2
Platform: UNKNOWN
Classifier: Environment :: Console
Classifier: License :: OSI Approved :: MIT License
Classifier: Natural Language :: English
Classifier: Operating System :: OS Independent
Classifier: Programming Language :: Python
Classifier: Programming Language :: Python :: 3
Classifier: Programming Language :: Python :: 3.6
Classifier: Programming Language :: Python :: 3.7
Classifier: Programming Language :: Python :: 3.8
Classifier: Programming Language :: Python :: Implementation :: CPython
Requires-Python: >=3.6
Requires-Dist: click (==7.*)
Requires-Dist: cryptography (==2.*)
Requires-Dist: pyperclip (==1.*)
Requires-Dist: requests (==2.*)
Requires-Dist: serde[ext] (==0.8.*)
Requires-Dist: tabulate (==0.8.*)
Requires-Dist: toml (==0.10.*)
